mseep_dbgpt_mono-0.7.2.dist-info/licenses/LICENSE
tests/__init__.py
mseep_dbgpt_mono-0.7.2.dist-info/METADATA
mseep_dbgpt_mono-0.7.2.dist-info/WHEEL
mseep_dbgpt_mono-0.7.2.dist-info/top_level.txt
mseep_dbgpt_mono-0.7.2.dist-info/RECORD
